arbeiter/__init__.py
arbeiter/_correct.py
arbeiter/_generate.py
arbeiter/exc.py
arbeiter/types.py
arbeiter-1.0.0.dist-info/METADATA
arbeiter-1.0.0.dist-info/WHEEL
arbeiter-1.0.0.dist-info/top_level.txt
arbeiter-1.0.0.dist-info/RECORD
