Metadata-Version: 2.1
Name: arbeiter
Version: 1.0.0
Summary: Correct and compute raw score of memory competitor's recall data
Home-page: https://gitlab.com/Penlect/arbeiter
Author: Daniel Andersson
Author-email: daniel.4ndersson@gmail.com
License: UNKNOWN
Keywords: memory memorization iam wmc recall
Platform: UNKNOWN
Classifier: Development Status :: 5 - Production/Stable
Classifier: Environment :: Console
Classifier: Intended Audience :: Other Audience
Classifier: Natural Language :: English
Classifier: Operating System :: Microsoft :: Windows :: Windows 10
Classifier: Operating System :: POSIX :: Linux
Classifier: Programming Language :: Python :: 3.6
Classifier: Programming Language :: Python :: 3.7
Classifier: Programming Language :: Python :: 3.8
Requires-Python: >=3.6
Requires-Dist: numpy
Requires-Dist: unidecode
